{"Diary Number": "12730 / 2008", "Case Number": "C.A. No.-004490-004490 / 2008", "Judgment link": "https://main.sci.gov.in/supremecourt/2008/12730/12730_2008_9_1502_20579_Judgement_14-Feb-2020.pdf", "Petitioner Name": "UNION OF INDIA", "Respondent Name": "M/S. ASSOCIATED CONTAINER TERMINAL LTD.", "Petitioner's Advocate": "B. KRISHNA PRASAD", "Respondent's Advocate": "RUPESH KUMAR", "Bench": "HON'BLE MR. JUSTICE L. NAGESWARA RAO, HON'BLE MR. JUSTICE HEMANT GUPTA", "Judgment By": "HON'BLE MR. JUSTICE L. NAGESWARA RAO", "Judgement Date": "14-02-2020", "Id": "2020_172"}