{"Diary Number": "18352 / 2015", "Case Number": "Crl.A. No.-000831-000831 / 2015", "Judgment link": "https://main.sci.gov.in/supremecourt/2015/18352/18352_2015_7_1503_19767_Judgement_21-Jan-2020.pdf", "Petitioner Name": "UNION OF INDIA", "Respondent Name": "R. KARTHIK", "Petitioner's Advocate": "MUKESH KUMAR MARORIA", "Bench": "HON'BLE MR. JUSTICE A.M. KHANWILKAR, HON'BLE MR. JUSTICE HEMANT GUPTA, HON'BLE MR. JUSTICE DINESH MAHESHWARI", "Judgment By": "HON'BLE MR. JUSTICE HEMANT GUPTA", "Judgement Date": "21-01-2020", "Id": "2020_246"}