{"Diary Number": "29760 / 2012", "Case Number": "Crl.A. No.-002035-002035 / 2012", "Judgment link": "https://main.sci.gov.in/supremecourt/2012/29760/29760_2012_1_1501_21549_Judgement_18-Mar-2020.pdf", "Petitioner Name": "EX-GUNNER VIRENDER PRASAD", "Respondent Name": "UNION OF INDIA", "Petitioner's Advocate": "B. K. PAL", "Respondent's Advocate": "MUKESH KUMAR MARORIA", "Bench": "HON'BLE THE CHIEF JUSTICE, HON'BLE MR. JUSTICE B.R. GAVAI, HON'BLE MR. JUSTICE SURYA KANT", "Judgment By": "HON'BLE THE CHIEF JUSTICE", "Judgement Date": "18-03-2020", "Id": "2020_382"}