{"Diary Number": "18989 / 2009", "Case Number": "C.A. No.-002573-002573 / 2020", "Judgment link": "https://main.sci.gov.in/supremecourt/2009/18989/18989_2009_32_1501_22617_Judgement_15-Jun-2020.pdf", "Petitioner Name": "VINODCHANDRA SAKARLAL KAPADIA", "Respondent Name": "STATE OF GUJARAT .", "Petitioner's Advocate": " LAWYER S KNIT & CO", "Respondent's Advocate": "ANIRUDDHA P. MAYEE", "Bench": "HON'BLE MR. JUSTICE UDAY UMESH LALIT, HON'BLE MR. JUSTICE MOHAN M. SHANTANAGOUDAR, HON'BLE MR. JUSTICE VINEET SARAN", "Judgment By": "HON'BLE MR. JUSTICE UDAY UMESH LALIT", "Judgement Date": "15-06-2020", "Id": "2020_252"}