{"Diary Number": "11326 / 2020", "Case Number": "C.A. No.-002964-002964 / 2020", "Judgment link": "https://main.sci.gov.in/supremecourt/2020/11326/11326_2020_35_1501_23479_Judgement_20-Aug-2020.pdf", "Petitioner Name": "SARDAR BAHGINDER SINGH", "Respondent Name": "SARDAR MANJIEETH SINGH", "Petitioner's Advocate": "SHASHIBHUSHAN P. ADGAONKAR", "Bench": "HON'BLE DR. JUSTICE D.Y. CHANDRACHUD, HON'BLE MS. JUSTICE INDU MALHOTRA, HON'BLE MR. JUSTICE K.M. JOSEPH", "Judgment By": "HON'BLE DR. JUSTICE D.Y. CHANDRACHUD", "Judgement Date": "20-08-2020", "Id": "2020_162"}