{"Diary Number": "7583 / 2017", "Case Number": "C.A. No.-000802-000802 / 2020", "Judgment link": "https://main.sci.gov.in/supremecourt/2017/7583/7583_2017_2_1501_20023_Judgement_29-Jan-2020.pdf", "Petitioner Name": "SHRIPAL BHATI ", "Respondent Name": "STATE OF UP ", "Petitioner's Advocate": "PURUSHOTTAM SHARMA TRIPATHI", "Bench": "HON'BLE MR. JUSTICE N.V. RAMANA, HON'BLE MR. JUSTICE SANJIV KHANNA, HON'BLE MR. JUSTICE KRISHNA MURARI", "Judgment By": "HON'BLE MR. JUSTICE KRISHNA MURARI", "Judgement Date": "29-01-2020", "Id": "2020_96"}