{"Diary Number": "39058 / 2017", "Case Number": "C.A. No.-020825-020826 / 2017", "Judgment link": "https://main.sci.gov.in/supremecourt/2017/39058/39058_2017_34_1501_22897_Judgement_14-Jul-2020.pdf", "Petitioner Name": "ARJUN PANDITRAO KHOTKAR", "Respondent Name": "KAILASH KUSHANRAO GORANTYAL", "Petitioner's Advocate": "RAVINDRA KESHAVRAO ADSURE", "Bench": "HON'BLE MR. JUSTICE ROHINTON FALI NARIMAN, HON'BLE MR. JUSTICE S. RAVINDRA BHAT, HON'BLE MR. JUSTICE V. RAMASUBRAMANIAN", "Judgment By": "HON'BLE MR. JUSTICE ROHINTON FALI NARIMAN", "Judgement Date": "14-07-2020", "Id": "2020_481"}