[{"Diary Number": "\u00a0", "Case Number": "Appeal (civil) 815 of 1963", "Judgment link": "https://main.sci.gov.in/jonew/judgment/judis/3373.pdf", "Petitioner Name": "VIDYACHARAN SHUKLA", "Respondent Name": "KHUBCHAND BAGHEL AND OTHERS", "Bench": "SINHA, BHUVNESHWAR P.(CJ),SUBBARAO, K.,DAYAL, RAGHUBAR,AYYANGAR, N. RAJAGOPALA,MUDHOLKAR, J.R."}, {"Diary Number": "834 / 1997", "Case Number": "C.A. No.-004323-004323 / 1999", "Judgment link": "https://main.sci.gov.in/jonew/judgment/judis/3413.pdf", "Petitioner Name": "R.P. KAPUR", "Respondent Name": "UNION OF INDIA .", "Respondent's Advocate": "SUSHMA SURI", "Bench": "GAJENDRAGADKAR, P.B.,SUBBARAO, K.,WANCHOO, K.N.,SHAH, J.C.,DAYAL, RAGHUBAR"}]