[{"Diary Number": "\u00a0", "Case Number": "Appeal (civil) 870 of 1973", "Judgment link": "https://main.sci.gov.in/jonew/judgment/judis/6370.pdf", "Petitioner Name": "HUKUMDEV NARAIN YADAV", "Respondent Name": "LALIT NARAIN MISHRA"}, {"Diary Number": "13987 / 1997", "Case Number": "Crl.A. No.-000980-000980 / 1997", "Judgment link": "https://main.sci.gov.in/jonew/judgment/judis/6386.pdf", "Petitioner Name": "VIJAY KUMAR", "Respondent Name": "STATE OF PUNJAB", "Petitioner's Advocate": "RAKESH K. SHARMA", "Bench": "CHANDRACHUD,Y.V."}]