{"Diary Number": "10631 / 2008", "Case Number": "Crl.A. No.-002007-002007 / 2008", "Judgment link": "https://main.sci.gov.in/supremecourt/2008/10631/10631_2008_Judgement_15-Feb-2019.pdf", "Petitioner Name": "EJAZHUSEN SABADARHUSEN .", "Respondent Name": "STATE OF GUJARAT", "Petitioner's Advocate": "RAHUL NARAYAN", "Respondent's Advocate": "HEMANTIKA WAHI", "Bench": "HON'BLE MR. JUSTICE A.M. KHANWILKAR, HON'BLE MR. JUSTICE AJAY RASTOGI", "Judgment By": "HON'BLE MR. JUSTICE A.M. KHANWILKAR", "Judgement Date": "15-02-2019", "Id": "2019_401"}