{"Diary Number": "10043 / 2017", "Case Number": "C.A. No.-008121 / 2019", "Judgment link": "https://main.sci.gov.in/supremecourt/2017/10043/10043_2017_9_1502_17294_Judgement_04-Oct-2019.pdf", "Petitioner Name": "IC 29547 L BOBBY JOSEPH", "Respondent Name": "UNION OF INDIA", "Petitioner's Advocate": "ALOK GUPTA", "Bench": "HON'BLE MR. JUSTICE L. NAGESWARA RAO, HON'BLE MR. JUSTICE HEMANT GUPTA", "Judgment By": "HON'BLE MR. JUSTICE L. NAGESWARA RAO", "Judgement Date": "04-10-2019", "Id": "2019_374"}