{"Diary Number": "12878 / 2009", "Case Number": "C.A. No.-009576-009576 / 2010", "Judgment link": "https://main.sci.gov.in/supremecourt/2009/12878/12878_2009_3_1501_16808_Judgement_17-Sep-2019.pdf", "Petitioner Name": "K. ARJUN DAS", "Respondent Name": "COMMISSIONER OF ENDOWMENTS, ORISSA", "Petitioner's Advocate": "PRANAB KUMAR MULLICK", "Respondent's Advocate": "SHASHI BHUSHAN KUMAR", "Bench": "HON'BLE MR. JUSTICE N.V. RAMANA, HON'BLE MR. JUSTICE MOHAN M. SHANTANAGOUDAR, HON'BLE MR. JUSTICE AJAY RASTOGI", "Judgment By": "HON'BLE MR. JUSTICE AJAY RASTOGI", "Judgement Date": "17-09-2019", "Id": "2019_496"}